colab/__init__.py
colab/colab.py
colab/th_column_names.py
colab/tianhua_local.py
colab_to_PETA-0.0.9.dist-info/LICENSE
colab_to_PETA-0.0.9.dist-info/METADATA
colab_to_PETA-0.0.9.dist-info/WHEEL
colab_to_PETA-0.0.9.dist-info/entry_points.txt
colab_to_PETA-0.0.9.dist-info/top_level.txt
colab_to_PETA-0.0.9.dist-info/RECORD
