Metadata-Version: 2.1
Name: colab-to-PETA
Version: 0.0.9
Summary: tools for curating colab gene test data to bgi-PETA.
Home-page: UNKNOWN
Author: JaylanLiu
Author-email: liujilong@outlook.com
License: UNKNOWN
Platform: UNKNOWN
Classifier: Development Status :: 3 - Alpha
Classifier: Intended Audience :: Developers
Classifier: Topic :: Scientific/Engineering :: Bio-Informatics
Classifier: License :: OSI Approved :: MIT License
Classifier: Programming Language :: Python :: 3.5
Classifier: Programming Language :: Python :: 3.6
Classifier: Programming Language :: Python :: 3.7
Requires-Python: >=3.6
License-File: LICENSE
Requires-Dist: sqlalchemy
Requires-Dist: pymysql
